README
setup.py
CustomSelectAdmin/__init__.py
CustomSelectAdmin/admin.py
CustomSelectAdmin.egg-info/PKG-INFO
CustomSelectAdmin.egg-info/SOURCES.txt
CustomSelectAdmin.egg-info/dependency_links.txt
CustomSelectAdmin.egg-info/entry_points.txt
CustomSelectAdmin.egg-info/top_level.txt