Metadata-Version: 1.0
Name: CustomSelectAdmin
Version: 0.6
Summary: Modify custom select fields for tickets in an admin panel within Trac.
Home-page: http://github.com/jetheis/CustomSelectAdmin
Author: Jimmy Theis
Author-email: jimmy@jetheis.com
License: GPLv3
Platform: UNKNOWN
